LICENSE
README.md
setup.cfg
setup.py
ac_utils/__init__.py
ac_utils/ac_utils.py
ac_utils.egg-info/PKG-INFO
ac_utils.egg-info/SOURCES.txt
ac_utils.egg-info/dependency_links.txt
ac_utils.egg-info/requires.txt
ac_utils.egg-info/top_level.txt