Metadata-Version: 2.1
Name: ac-utils
Version: 0.1.3
Summary: Functions for working with robotics.
Home-page: https://github.com/AlbertoCruzRuiz/ac_utils
Download-URL: https://github.com/AlbertoCruzRuiz/ac_utils/archive/refs/tags/v0.1.tar.gz
Author: Alberto Cruz
Author-email: alberto.cruz@upm.es
License: GNU General Public License v3.0
Keywords: Robotics
Classifier: Development Status :: 3 - Alpha
Classifier: Intended Audience :: Developers
Classifier: Topic :: Software Development :: Build Tools
Classifier: License :: OSI Approved :: GNU General Public License v3 (GPLv3)
Classifier: Programming Language :: Python :: 3.10
License-File: LICENSE
